pycfslib/__init__.py
pycfslib-0.4.dist-info/DESCRIPTION.rst
pycfslib-0.4.dist-info/METADATA
pycfslib-0.4.dist-info/RECORD
pycfslib-0.4.dist-info/WHEEL
pycfslib-0.4.dist-info/metadata.json
pycfslib-0.4.dist-info/top_level.txt
