Metadata-Version: 2.0
Name: pycfslib
Version: 0.4
Summary: Library to read, write and create CFS file and stream.
Home-page: http://github.com/amiyapatanaik/pycfslib
Author: Amiya Patanaik
Author-email: amiya@duke-nus.edu.sg
License: GPL
Platform: UNKNOWN
Requires-Dist: numba
Requires-Dist: numpy
Requires-Dist: scipy
